RiSA/__init__.py
RiSA/__version__.py
RiSA/download.py
RiSA/frequency_analysis.py
RiSA/geo_tools.py
RiSA/hydro_tools.py
RiSA/libraries.py
RiSA/master_results.py
RiSA/results.py
RiSA/rg_pre.py
RiSA/tools.py
pydrodesign-1.0.1.dist-info/LICENSE
pydrodesign-1.0.1.dist-info/METADATA
pydrodesign-1.0.1.dist-info/WHEEL
pydrodesign-1.0.1.dist-info/top_level.txt
pydrodesign-1.0.1.dist-info/RECORD
