Metadata-Version: 2.1
Name: pydrodesign
Version: 1.0.1
Summary: Tools for Hydrology Design.
Home-page: https://github.com/joaquinseguraellis/PydroDesign
Author: Joaquin Sebastian Segura Ellis
Author-email: joaquin.segura.ellis@mi.unc.edu.ar
Project-URL: Bug Tracker, https://github.com/joaquinseguraellis/PydroDesign/issues
Classifier: Natural Language :: English
Classifier: Programming Language :: Python :: 3
Classifier: License :: OSI Approved :: MIT License
Classifier: Operating System :: Microsoft :: Windows :: Windows 10
Classifier: Operating System :: Microsoft :: Windows :: Windows 11
Classifier: Development Status :: 2 - Pre-Alpha
Classifier: Intended Audience :: Science/Research
Classifier: Topic :: Scientific/Engineering :: Hydrology
Requires-Python: >=3.6
License-File: LICENSE
